sphinx_ape/__init__.py
sphinx_ape/_base.py
sphinx_ape/_cli.py
sphinx_ape/_utils.py
sphinx_ape/build.py
sphinx_ape/exceptions.py
sphinx_ape/py.typed
sphinx_ape/testing.py
sphinx_ape/types.py
sphinx_ape/version.py
sphinx_ape/_static/custom.css
sphinx_ape/_static/favicon.ico
sphinx_ape/_static/logo.gif
sphinx_ape/_static/logo_green.svg
sphinx_ape/_static/logo_grey.svg
sphinx_ape/sphinx_ext/__init__.py
sphinx_ape/sphinx_ext/directives.py
sphinx_ape/sphinx_ext/plugin.py
sphinx_ape-0.1.2.dist-info/licenses/LICENSE
sphinx_ape-0.1.2.dist-info/METADATA
sphinx_ape-0.1.2.dist-info/WHEEL
sphinx_ape-0.1.2.dist-info/entry_points.txt
sphinx_ape-0.1.2.dist-info/top_level.txt
sphinx_ape-0.1.2.dist-info/RECORD
