Metadata-Version: 2.4
Name: sphinx-ape
Version: 0.1.2
Summary: sphinx-ape: Build Sphinx Documentation for ApeWorX plugins
Author-email: "ApeWorX Ltd." <admin@apeworx.io>
License-Expression: Apache-2.0
Project-URL: Repository, https://github.com/ApeWorX/sphinx-ape
Project-URL: Issues, https://github.com/ApeWorX/sphinx-ape/issues
Project-URL: Documentation, https://docs.apeworx.io/sphinx-ape
Keywords: etheruem,ape,sphinx
Classifier: Development Status :: 5 - Production/Stable
Classifier: Intended Audience :: Developers
Classifier: Natural Language :: English
Classifier: Operating System :: MacOS
Classifier: Operating System :: POSIX
Classifier: Operating System :: Microsoft :: Windows
Classifier: Programming Language :: Python :: 3
Classifier: Programming Language :: Python :: 3.10
Classifier: Programming Language :: Python :: 3.11
Classifier: Programming Language :: Python :: 3.12
Classifier: Programming Language :: Python :: 3.13
Classifier: Programming Language :: Python :: 3.14
Requires-Python: <4,>=3.10
License-File: LICENSE
Requires-Dist: click<9,>=8.1.7
Requires-Dist: tomli<3,>=1.2.3
Requires-Dist: shibuya
Requires-Dist: pygments<3,>=2.17.0
Requires-Dist: myst-parser<5,>=4.0.0
Requires-Dist: sphinx-click<7,>=6.0.0
Requires-Dist: Sphinx<9,>=8.1.3
Requires-Dist: sphinx_rtd_theme<4,>=3.0.1
Requires-Dist: sphinxcontrib-napoleon<0.8,>=0.7
Requires-Dist: sphinx-plausible<0.2,>=0.1.2
Dynamic: license-file
